tgzr/hosts/harmony/__init__.py
tgzr/hosts/harmony/_version.py
tgzr/hosts/harmony/startup.py
tgzr/hosts/harmony/cli/__init__.py
tgzr/hosts/harmony/cli/plugins_cli.py
tgzr/hosts/harmony/cli/settings_cli.py
tgzr/hosts/harmony/default_plugins/the_panel/__init__.py
tgzr/hosts/harmony/default_plugins/the_panel/gui.py
tgzr/hosts/harmony/default_plugins/the_panel/plugin.py
tgzr/hosts/harmony/default_plugins/xsheet/__init__.py
tgzr/hosts/harmony/default_plugins/xsheet/cli.py
tgzr/hosts/harmony/default_plugins/xsheet/gui.py
tgzr/hosts/harmony/default_plugins/xsheet/plugin.py
tgzr/hosts/harmony/default_plugins/xsheet/xsheet.py
tgzr/hosts/harmony/external_script_packages_folder/__init__.py
tgzr/hosts/harmony/external_script_packages_folder/tgzr_harmony_startup/configure.js
tgzr/hosts/harmony/external_script_packages_folder/tgzr_harmony_startup/startup.py
tgzr/hosts/harmony/external_script_packages_folder/tgzr_harmony_startup/icons/tgzr_thumbnail.png
tgzr/hosts/harmony/launch/__init__.py
tgzr/hosts/harmony/launch/example.env
tgzr/hosts/harmony/launch/settings.py
tgzr/hosts/harmony/plugin/__init__.py
tgzr/hosts/harmony/shell_app/__init__.py
tgzr/hosts/harmony/shell_cli/__init__.py
tgzr_hosts_harmony-0.100.dist-info/METADATA
tgzr_hosts_harmony-0.100.dist-info/WHEEL
tgzr_hosts_harmony-0.100.dist-info/entry_points.txt
tgzr_hosts_harmony-0.100.dist-info/licenses/LICENSE
tgzr_hosts_harmony-0.100.dist-info/RECORD
