Metadata-Version: 2.4
Name: tgzr.hosts.harmony
Version: 0.100
Summary: Toonboom Harmony integration in tgzr.
Project-URL: Documentation, https://github.com/open-tgzr/tgzr.hosts.harmony#readme
Project-URL: Issues, https://github.com/open-tgzr/tgzr.hosts.harmony/issues
Project-URL: Source, https://github.com/open-tgzr/tgzr.hosts.harmony
Author-email: Dee <dee.sometech@gmail.com>
License-Expression: GPL-3.0-or-later
License-File: LICENSE
Classifier: Development Status :: 4 - Beta
Classifier: Programming Language :: Python
Classifier: Programming Language :: Python :: 3.9
Classifier: Programming Language :: Python :: 3.10
Classifier: Programming Language :: Python :: 3.11
Classifier: Programming Language :: Python :: 3.12
Classifier: Programming Language :: Python :: Implementation :: CPython
Classifier: Programming Language :: Python :: Implementation :: PyPy
Requires-Python: >=3.9
Requires-Dist: click>=8.1.8
Requires-Dist: pydantic-settings>=2.11.0
Requires-Dist: pydantic>=2.12.5
Requires-Dist: rich>=14.2.0
Requires-Dist: tgzr-package-management>=0.100
